formatforge/__init__.py
formatforge/main.py
formatforge/uppercase.py
formatforge-0.1.2.dist-info/LICENSE.md
formatforge-0.1.2.dist-info/METADATA
formatforge-0.1.2.dist-info/WHEEL
formatforge-0.1.2.dist-info/entry_points.txt
formatforge-0.1.2.dist-info/RECORD
