Metadata-Version: 2.1
Name: formatforge
Version: 0.1.2
Summary: A simple linter for dbt projects
Author: Rawlsy-py
Author-email: christopher_m_mitchell@live.co.uk
Requires-Python: >=3.11,<4.0
Classifier: Programming Language :: Python :: 3
Classifier: Programming Language :: Python :: 3.11
Requires-Dist: pydantic (>=2.6.3,<3.0.0)
Requires-Dist: typer[all] (>=0.9.0,<0.10.0)
